standard_chatml/__init__.py
standard_chatml-0.0.1.dist-info/METADATA
standard_chatml-0.0.1.dist-info/WHEEL
standard_chatml-0.0.1.dist-info/RECORD
