Metadata-Version: 2.1
Name: standard-chatml
Version: 0.0.1
Summary: Standardized spec and vendor-specific transforms for ChatML
License: MIT
Author: Diwank Tomer
Author-email: diwank@julep.ai
Requires-Python: >=3.10,<4.0
Classifier: License :: OSI Approved :: MIT License
Classifier: Programming Language :: Python :: 3
Classifier: Programming Language :: Python :: 3.10
Classifier: Programming Language :: Python :: 3.11
Classifier: Programming Language :: Python :: 3.12
